stackit/serviceaccount/__init__.py
stackit/serviceaccount/api/__init__.py
stackit/serviceaccount/api/default_api.py
stackit/serviceaccount/api_client.py
stackit/serviceaccount/api_response.py
stackit/serviceaccount/configuration.py
stackit/serviceaccount/exceptions.py
stackit/serviceaccount/models/__init__.py
stackit/serviceaccount/models/access_token.py
stackit/serviceaccount/models/access_token_metadata.py
stackit/serviceaccount/models/auth_error.py
stackit/serviceaccount/models/auth_error_error.py
stackit/serviceaccount/models/create_access_token_payload.py
stackit/serviceaccount/models/create_service_account_key_payload.py
stackit/serviceaccount/models/create_service_account_key_response.py
stackit/serviceaccount/models/create_service_account_key_response_credentials.py
stackit/serviceaccount/models/create_service_account_payload.py
stackit/serviceaccount/models/create_short_lived_access_token_response.py
stackit/serviceaccount/models/error.py
stackit/serviceaccount/models/get_service_account_key_response.py
stackit/serviceaccount/models/get_service_account_key_response_credentials.py
stackit/serviceaccount/models/jwk.py
stackit/serviceaccount/models/jwks.py
stackit/serviceaccount/models/list_access_tokens_response.py
stackit/serviceaccount/models/list_service_account_keys_response.py
stackit/serviceaccount/models/list_service_accounts_response.py
stackit/serviceaccount/models/partial_update_service_account_key_payload.py
stackit/serviceaccount/models/partial_update_service_account_key_response.py
stackit/serviceaccount/models/service_account.py
stackit/serviceaccount/models/service_account_key_list_response.py
stackit/serviceaccount/py.typed
stackit/serviceaccount/rest.py
stackit_serviceaccount-0.4.2.dist-info/METADATA
stackit_serviceaccount-0.4.2.dist-info/WHEEL
stackit_serviceaccount-0.4.2.dist-info/licenses/LICENSE.md
stackit_serviceaccount-0.4.2.dist-info/licenses/NOTICE.txt
stackit_serviceaccount-0.4.2.dist-info/RECORD
